rustic_ai/core/__init__.py
rustic_ai/core/agents/__init__.py
rustic_ai/core/agents/commons/__init__.py
rustic_ai/core/agents/commons/classify_extract.py
rustic_ai/core/agents/commons/image_generation.py
rustic_ai/core/agents/commons/media.py
rustic_ai/core/agents/commons/message_formats.py
rustic_ai/core/agents/eip/__init__.py
rustic_ai/core/agents/eip/aggregating_agent.py
rustic_ai/core/agents/eip/basic_wiring_agent.py
rustic_ai/core/agents/eip/splitter_agent.py
rustic_ai/core/agents/indexing/__init__.py
rustic_ai/core/agents/indexing/knowledge_agent.py
rustic_ai/core/agents/indexing/vector_agent.py
rustic_ai/core/agents/llm/__init__.py
rustic_ai/core/agents/llm/simple_llm_agent.py
rustic_ai/core/agents/planners/__init__.py
rustic_ai/core/agents/planners/todolist_agent.py
rustic_ai/core/agents/system/__init__.py
rustic_ai/core/agents/system/guild_manager_agent.py
rustic_ai/core/agents/system/guild_manager_agent_props.py
rustic_ai/core/agents/system/models.py
rustic_ai/core/agents/testutils/__init__.py
rustic_ai/core/agents/testutils/echo_agent.py
rustic_ai/core/agents/testutils/probe_agent.py
rustic_ai/core/agents/testutils/ui_component_agent.py
rustic_ai/core/agents/utils/__init__.py
rustic_ai/core/agents/utils/http_client.py
rustic_ai/core/agents/utils/user_proxy_agent.py
rustic_ai/core/guild/__init__.py
rustic_ai/core/guild/agent.py
rustic_ai/core/guild/agent_ext/__init__.py
rustic_ai/core/guild/agent_ext/depends/__init__.py
rustic_ai/core/guild/agent_ext/depends/code_execution/__init__.py
rustic_ai/core/guild/agent_ext/depends/code_execution/data_analyzer/__init__.py
rustic_ai/core/guild/agent_ext/depends/code_execution/data_analyzer/analyzer.py
rustic_ai/core/guild/agent_ext/depends/code_execution/data_analyzer/exceptions.py
rustic_ai/core/guild/agent_ext/depends/code_execution/data_analyzer/models.py
rustic_ai/core/guild/agent_ext/depends/code_execution/data_analyzer/tools.py
rustic_ai/core/guild/agent_ext/depends/code_execution/stateful/__init__.py
rusticai_core-1.0.0.dist-info/METADATA
rusticai_core-1.0.0.dist-info/WHEEL
rusticai_core-1.0.0.dist-info/RECORD
